<?xml version="1.0" encoding="UTF-8"?> <!-- Esta linea se repite en cadaarchivo XML -->

<!-- Solo puede haber in nodo raiz (tiene que ser unico) -->

<biblioteca>

    <!-- Dentro del nodo raiz (biblioteca) puede haber mas nodos y estos se pueden repetir infinitamente con el mismo nombre-->

    <libro>
        <titulo></titulo>
        <autor></autor>
        <isbn></isbn>
    </libro>

    <libro>
        <titulo></titulo>
        <autor></autor>
        <isbn></isbn>
    </libro>
    
    <libro>
        <titulo></titulo>
        <autor></autor>
        <isbn></isbn>
    </libro>
</biblioteca>